sphinx_defectdojo/__init__.py
sphinx_defectdojo/finding.py
sphinx_defectdojo-2023.11.20.4.dist-info/LICENSE
sphinx_defectdojo-2023.11.20.4.dist-info/METADATA
sphinx_defectdojo-2023.11.20.4.dist-info/WHEEL
sphinx_defectdojo-2023.11.20.4.dist-info/top_level.txt
sphinx_defectdojo-2023.11.20.4.dist-info/RECORD
