Metadata-Version: 2.1
Name: sphinx-defectdojo
Version: 2023.11.20.4
Summary: A minimal system to make documenting findings in DefectDojo easier with Sphinx via lazy reference
Author-email: Chris Halbersma <chalbersma@auditboard.com>
License: BSD-3-Clause
Keywords: defectDojo
Classifier: Programming Language :: Python :: 3
Requires-Python: >=3.11
License-File: LICENSE
Requires-Dist: dojo-truant
